setuptools_golang.py
setuptools_golang-2.9.0.dist-info/LICENSE
setuptools_golang-2.9.0.dist-info/METADATA
setuptools_golang-2.9.0.dist-info/WHEEL
setuptools_golang-2.9.0.dist-info/entry_points.txt
setuptools_golang-2.9.0.dist-info/top_level.txt
setuptools_golang-2.9.0.dist-info/RECORD
