Metadata-Version: 2.1
Name: setuptools-golang
Version: 2.9.0
Summary: A setuptools extension for building cpython extensions written in golang.
Home-page: https://github.com/asottile/setuptools-golang
Author: Anthony Sottile
Author-email: asottile@umich.edu
License: MIT
Classifier: License :: OSI Approved :: MIT License
Classifier: Programming Language :: Python :: 3
Classifier: Programming Language :: Python :: 3 :: Only
Classifier: Programming Language :: Python :: Implementation :: CPython
Classifier: Programming Language :: Python :: Implementation :: PyPy
Requires-Python: >=3.8
License-File: LICENSE
Requires-Dist: setuptools
